pretix_payonegopay/__init__.py
pretix_payonegopay/apps.py
pretix_payonegopay/payment.py
pretix_payonegopay/paymentmethods.py
pretix_payonegopay/signals.py
pretix_payonegopay/urls.py
pretix_payonegopay/static/pretix_payonegopay/logo.svg
pretix_worldlinedirect/__init__.py
pretix_worldlinedirect/apps.py
pretix_worldlinedirect/payment.py
pretix_worldlinedirect/paymentmethods.py
pretix_worldlinedirect/signals.py
pretix_worldlinedirect/urls.py
pretix_worldlinedirect/views.py
pretix_worldlinedirect/locale/de/LC_MESSAGES/django.mo
pretix_worldlinedirect/locale/de/LC_MESSAGES/django.po
pretix_worldlinedirect/locale/de_Informal/.gitkeep
pretix_worldlinedirect/locale/de_Informal/LC_MESSAGES/django.mo
pretix_worldlinedirect/locale/de_Informal/LC_MESSAGES/django.po
pretix_worldlinedirect/static/pretix_worldlinedirect/.gitkeep
pretix_worldlinedirect/static/pretix_worldlinedirect/logo.svg
pretix_worldlinedirect/templates/pretix_worldlinedirect/.gitkeep
pretix_worldlinedirect/templates/pretix_worldlinedirect/checkout_payment_confirm.html
pretix_worldlinedirect/templates/pretix_worldlinedirect/checkout_payment_form.html
pretix_worldlinedirect/templates/pretix_worldlinedirect/control.html
pretix_worldlinedirect/templates/pretix_worldlinedirect/pending.html
pretix_worldlinedirect-1.1.0.dist-info/licenses/LICENSE
pretix_worldlinedirect-1.1.0.dist-info/METADATA
pretix_worldlinedirect-1.1.0.dist-info/WHEEL
pretix_worldlinedirect-1.1.0.dist-info/entry_points.txt
pretix_worldlinedirect-1.1.0.dist-info/top_level.txt
pretix_worldlinedirect-1.1.0.dist-info/RECORD
