Metadata-Version: 2.4
Name: pretix-worldlinedirect
Version: 1.1.0
Summary: Accept payments through Worldline Direct
Author-email: pretix team <support@pretix.eu>
Maintainer-email: pretix team <support@pretix.eu>
License: Apache
Project-URL: homepage, https://github.com/pretix/pretix-worldlinedirect/
Project-URL: repository, https://github.com/pretix/pretix-worldlinedirect/
Keywords: pretix
License-File: LICENSE
Requires-Dist: onlinepayments-sdk-python3==4.23.*
Dynamic: license-file
